encrypted_fields/__init__.py
encrypted_fields/fields.py
django_fernet_encrypted_fields-0.3.0.dist-info/LICENCE.txt
django_fernet_encrypted_fields-0.3.0.dist-info/METADATA
django_fernet_encrypted_fields-0.3.0.dist-info/WHEEL
django_fernet_encrypted_fields-0.3.0.dist-info/top_level.txt
django_fernet_encrypted_fields-0.3.0.dist-info/RECORD
