Metadata-Version: 2.1
Name: django-fernet-encrypted-fields
Version: 0.3.0
Summary: This is inspired by django-encrypted-fields.
Home-page: http://github.com/jazzband/django-fernet-encrypted-fields/
Author: jazzband
Author-email: n.anahara@fragment.co.jp
License: MIT
License-File: LICENCE.txt
Requires-Dist: Django>=3.2
Requires-Dist: cryptography>=35.0.0
